{"cameraMode":{"drawMode":0,"name":"Shaded","section":"Shading Mode"},"sceneLighting":true,"audioPlay":false,"sceneViewState":{"m_AlwaysRefresh":false,"showFog":true,"showSkybox":true,"showFlares":true,"showImageEffects":true,"showParticleSystems":true,"showVisualEffectGraphs":true,"m_FxEnabled":false},"in2DMode":false,"pivot":{"x":2.2702956199645998,"y":-0.8801885843276978,"z":0.06017716974020004},"rotation":{"x":0.3159668743610382,"y":0.582126259803772,"z":-0.2620599567890167,"w":0.7018836736679077},"size":14.1818265914917,"orthographic":false}